student90001/__init__.py
student90001/student90001.py
zaheen-1.2.dist-info/METADATA
zaheen-1.2.dist-info/WHEEL
zaheen-1.2.dist-info/top_level.txt
zaheen-1.2.dist-info/RECORD
